mersal_sqlalchemy/__init__.py
mersal_sqlalchemy/orm.py
mersal_sqlalchemy/py.typed
mersal_sqlalchemy/sqlalchemy_outbox_storage.py
mersal_sqlalchemy/sqlalchemy_saga_storage.py
mersal_sqlalchemy/sqlalchemy_unit_of_work.py
mersal_sqlalchemy-0.1.0.dist-info/METADATA
mersal_sqlalchemy-0.1.0.dist-info/WHEEL
mersal_sqlalchemy-0.1.0.dist-info/RECORD
