Metadata-Version: 2.4
Name: mersal_sqlalchemy
Version: 0.1.0
Summary: SQLAlchemy support for Mersal
Author-email: Abdulhaq Emhemmed <abdulhaq.emhemmed@gmail.com>
Requires-Python: >=3.10
Requires-Dist: mersal
Requires-Dist: sqlalchemy
